{"tagline":"Z-Force Sample Code Repository","note":"Don't delete this file! It's used internally to help with page regeneration.","name":"Zuora ZCommerce","google":"","body":"**Zuora Z-Force Sample Code Suite**\r\n--\r\n\r\n**Introduction**\r\n--\r\n\r\nThe Z-Force Sample Code Suite provides executable code examples in unmanaged Force.com packages. \r\n\r\nZuora Support does not troubleshoot content from GitHub. The sample code is as an example of code \r\nthat has worked for previous implementations and was created by both Zuora and non-Zuora authors. \r\nPlease send any GitHub-related comments and feedback to Dev-Support@zuora.\r\n\r\n**Pre-Requisites**\r\n--\r\n\r\n* The Z-Force Sample Code Suite includes a set of unmanaged packages that depend on the following Z-Force managed packages:\r\n  * Z-Force 360 Version 2.2 or above\r\n  * Z-Force Quotes Version 5.3 or above\r\n\r\n* If you do not have Force.com Migration Tool already installed and you would like to use the Force.com Migration Tool to deploy the sample code to your Salesforce.com organization, please follow the instructions below: \r\n  * Visit http://java.sun.com/javase/downloads/index.jsp and install Java JDK, Version 6.1 or greater on the deployment machine.\r\n  * Visit http://ant.apache.org/ and install Apache Ant, Version 1.6 or greater on the deployment machine.\r\n  * Set up the environment variables (such as ANT_HOME, JAVA_HOME, and PATH) as specified in the Ant Installation Guide at http://ant.apache.org/manual/install.html.\r\n  * Log in to Salesforce on your deployment machine. Click Your Name | Setup | Develop | Tools, then click Force.com Migration Tool.\r\n  * Unzip the downloaded file to the directory of your choice. The Zip file contains a Jar file containing the ant tasks: ant-salesforce.jar\r\n  * Copy the ant-salesforce.jar file from the unzipped file into the ant lib directly.  The ant lib directly is located in the root folder of your Ant installation. \r\n\r\n**Installation Instructions**\r\n--\r\n\r\n* Open ZForce/build.properties, and specify the login credentials for your Salesforce.com organization: \r\n\r\n    >sf.username=\r\n    \r\n    >sf.password= \r\n\r\nPlease note that the password should be your login password concatenated with the security token.\r\n\r\n* Navigate to Z-Force folder, and type the following in the command line: \r\n\r\n    >ant deploy\r\n\r\nThis will deploy all sample code packages to your Salesforce.com organization.\r\n\r\nOptionally, you can deploy one or more sample code packages individually into one or more Salesforce.com organizations. \r\n  * Navigate to Z-Force/<Sample Code Package> folder, for instance, Z-Force/InvoiceOwnerTransfer\r\n  * Open build.properties file, and specify the login credentials for your Salesforce.com organization (for this specific sample code package)\r\n\r\n    >sf.username=    \r\n    >sf.password= \r\n    \r\n* In command-line, type:\r\n\r\n    >ant deploy\r\n\r\nThis will deploy the specific sample code package into your Salesforce.com organization."}